IRONbark/IRONError.py
IRONbark/Module.py
IRONbark/__init__.py
IRONbark-1.2.2.dist-info/LICENSE
IRONbark-1.2.2.dist-info/METADATA
IRONbark-1.2.2.dist-info/WHEEL
IRONbark-1.2.2.dist-info/top_level.txt
IRONbark-1.2.2.dist-info/RECORD
