Metadata-Version: 2.1
Name: IRONbark
Version: 1.2.2
Summary: Inter Process Communication
Home-page: https://github.com/Zentetsu/IRONbark
Author: Zentetsu
License: GPLv3
Requires-Python: >=3.10
License-File: LICENSE
Requires-Dist: SharedMemory
Requires-Dist: numpy
